{
  "id": "5ae4fb33-e97e-450a-b9cf-a5a31fe9d204",
  "context_id": "4aaf8c53-61c8-49e1-af58-bb964a87345e",
  "operation": "Create",
  "data": {
    "created_at": "2025-03-19T23:10:57.905333700Z",
    "data": {
      "test": true
    },
    "expires_at": null,
    "id": "4aaf8c53-61c8-49e1-af58-bb964a87345e",
    "metadata": null,
    "name": "test_context",
    "parent_id": null,
    "updated_at": "2025-03-19T23:10:57.905334Z"
  },
  "timestamp": "2025-03-19T23:10:57.905373800Z",
  "version": 87
}